reddit_cssfilter
