Metadata-Version: 1.1
Name: reddit-cssfilter
Version: 1.2
Summary: Parse and validate a safe subset of CSS
Home-page: https://github.com/andychase/reddit-cssfilter
Author: reddit
Author-email: reddit@reddit.com
License: Common Public Attribution License Version 1.0 (CPAL)
Download-URL: https://github.com/andychase/reddit-cssfilter/archive/master.zip
Platform: UNKNOWN
Classifier: Development Status :: 4 - Beta
Classifier: Intended Audience :: Developers
Classifier: Natural Language :: English
Classifier: License :: OSI Approved
Classifier: Programming Language :: Python
Classifier: Programming Language :: Python :: 2.7
Classifier: Programming Language :: Python :: 3
Classifier: Programming Language :: Python :: 3.3
Classifier: Programming Language :: Python :: 3.4
Classifier: Programming Language :: Python :: 3.5
